parsipy/__init__.py
parsipy/__main__.py
parsipy/data.py
parsipy/p2t.py
parsipy/params.py
parsipy/pipeline.py
parsipy/pos_tagger.py
parsipy/tokenizer.py
parsipy/word_stemmer.py
parsipy/files/emission.csv
parsipy/files/roots.json
parsipy/files/stems.csv
parsipy/files/transition.csv
parsipy-0.1.dist-info/licenses/AUTHORS.md
parsipy-0.1.dist-info/licenses/LICENSE
parsipy-0.1.dist-info/METADATA
parsipy-0.1.dist-info/WHEEL
parsipy-0.1.dist-info/top_level.txt
parsipy-0.1.dist-info/RECORD
